{
    "pageNumber": 0,
    "data": [
        {
            "id": "133182085",
            "title": "DIY Gifting for Coffee Lovers",
            "date_created": "1513098723",
            "loginId": "1758166",
            "tags": "",
            "description": "DIY Gifting for Coffee Lovers",
            "asset": {
                "user": {
                    "firstName": "",
                    "lastName": "",
                    "emailAddress": ""
                },
                "videoMeta": {
                    "duration": "33",
                    "width": 1080,
                    "height": 1080
                },
                "mediaDuration": "33",
                "prettyDuration": "00:00:33",
                "thumbnailUrl": "\/\/v.tvpage.com\/1758166\/133182085\/12839\/thumb-3be47a4e2be1a091d32dc4744cfe0817-00001.jpg",
                "type": "mp4",
                "dashUrl": "\/\/v.tvpage.com\/1758166\/133182085\/12839\/media.mpd",
                "hlsUrl": "\/\/v.tvpage.com\/1758166\/133182085\/12839\/media.m3u8",
                "uploadAsset": false,
                "quality": "",
                "cc": [
                    {
                        "label": "English",
                        "srclang": "en",
                        "src": "\/\/v.tvpage.com\/1758166\/133182085\/cc\/vtt\/en_1516751523.vtt",
                        "default": true
                    }
                ],
                "sources": [
                    {
                        "file": "\/\/v.tvpage.com\/1758166\/133182085\/12839\/1080p_media.mp4",
                        "quality": "1080p",
                        "mime": "video\/mp4",
                        "width": 1080,
                        "height": 1080
                    },
                    {
                        "file": "\/\/v.tvpage.com\/1758166\/133182085\/12839\/720p_media.mp4",
                        "quality": "720p",
                        "mime": "video\/mp4",
                        "width": 720,
                        "height": 720
                    },
                    {
                        "file": "\/\/v.tvpage.com\/1758166\/133182085\/12839\/480p_media.mp4",
                        "quality": "480p",
                        "mime": "video\/mp4",
                        "width": 480,
                        "height": 480
                    },
                    {
                        "file": "\/\/v.tvpage.com\/1758166\/133182085\/12839\/360p_media.mp4",
                        "quality": "360p",
                        "mime": "video\/mp4",
                        "width": 360,
                        "height": 360
                    },
                    {
                        "file": "\/\/v.tvpage.com\/1758166\/133182085\/12839\/240p_media.mp4",
                        "quality": "240p",
                        "mime": "video\/mp4",
                        "width": 240,
                        "height": 240
                    }
                ]
            },
            "parentId": "6410338",
            "url": "\/gifting\/jetsetter-holiday2017-mp4\/6410338-133182085"
        },
        {
            "id": "132348265",
            "title": "Use the Present as the Packaging",
            "date_created": "1512399034",
            "loginId": "1758166",
            "tags": "",
            "description": "Here's a unique gift wrapping idea on how to use part of the present as the gift wrap.",
            "asset": {
                "user": {
                    "firstName": "",
                    "lastName": "",
                    "emailAddress": ""
                },
                "videoMeta": {
                    "duration": "41",
                    "width": 1920,
                    "height": 1080
                },
                "mediaDuration": "41",
                "prettyDuration": "00:00:41",
                "thumbnailUrl": "\/\/sitecdn.tvpage.com\/live\/users\/1758166\/canvas\/1920\/1077\/141749447-0219201079.jpg",
                "type": "mp4",
                "dashUrl": "\/\/v.tvpage.com\/1758166\/132348265\/d7d40\/media.mpd",
                "hlsUrl": "\/\/v.tvpage.com\/1758166\/132348265\/d7d40\/media.m3u8",
                "uploadAsset": false,
                "quality": "",
                "sources": [
                    {
                        "file": "\/\/v.tvpage.com\/1758166\/132348265\/d7d40\/1080p_media.mp4",
                        "quality": "1080p",
                        "mime": "video\/mp4",
                        "width": 1920,
                        "height": 1080
                    },
                    {
                        "file": "\/\/v.tvpage.com\/1758166\/132348265\/d7d40\/720p_media.mp4",
                        "quality": "720p",
                        "mime": "video\/mp4",
                        "width": 1280,
                        "height": 720
                    },
                    {
                        "file": "\/\/v.tvpage.com\/1758166\/132348265\/d7d40\/480p_media.mp4",
                        "quality": "480p",
                        "mime": "video\/mp4",
                        "width": 854,
                        "height": 480
                    },
                    {
                        "file": "\/\/v.tvpage.com\/1758166\/132348265\/d7d40\/360p_media.mp4",
                        "quality": "360p",
                        "mime": "video\/mp4",
                        "width": 640,
                        "height": 360
                    },
                    {
                        "file": "\/\/v.tvpage.com\/1758166\/132348265\/d7d40\/240p_media.mp4",
                        "quality": "240p",
                        "mime": "video\/mp4",
                        "width": 320,
                        "height": 180
                    }
                ],
                "cc": [
                    {
                        "label": "English",
                        "srclang": "en",
                        "src": "\/\/v.tvpage.com\/1758166\/132348265\/cc\/vtt\/en_1516752039.vtt",
                        "default": true
                    }
                ]
            },
            "parentId": "6410338",
            "url": "\/gifting\/blanketwhite-mp4\/6410338-132348265"
        },
        {
            "id": "132348266",
            "title": "Wrap an Odd-Shaped Gift: Fitness",
            "date_created": "1512399082",
            "loginId": "1758166",
            "tags": "",
            "description": "Have a fantastic gift, but it's a bit cumbersome to wrap? Here is a suggestion on how to present those odd-shaped presents.",
            "asset": {
                "user": {
                    "firstName": "",
                    "lastName": "",
                    "emailAddress": ""
                },
                "videoMeta": {
                    "duration": "33",
                    "width": 1920,
                    "height": 1080
                },
                "mediaDuration": "33",
                "prettyDuration": "00:00:33",
                "thumbnailUrl": "\/\/sitecdn.tvpage.com\/live\/users\/1758166\/canvas\/1920\/1077\/100082190-0219201079.jpg",
                "type": "mp4",
                "dashUrl": "\/\/v.tvpage.com\/1758166\/132348266\/b68f4\/media.mpd",
                "hlsUrl": "\/\/v.tvpage.com\/1758166\/132348266\/b68f4\/media.m3u8",
                "uploadAsset": false,
                "quality": "",
                "cc": [
                    {
                        "label": "English",
                        "srclang": "en",
                        "src": "\/\/v.tvpage.com\/1758166\/132348266\/cc\/vtt\/en_1516390789.vtt",
                        "default": true
                    }
                ],
                "sources": [
                    {
                        "file": "\/\/v.tvpage.com\/1758166\/132348266\/b68f4\/1080p_media.mp4",
                        "quality": "1080p",
                        "mime": "video\/mp4",
                        "width": 1920,
                        "height": 1080
                    },
                    {
                        "file": "\/\/v.tvpage.com\/1758166\/132348266\/b68f4\/720p_media.mp4",
                        "quality": "720p",
                        "mime": "video\/mp4",
                        "width": 1280,
                        "height": 720
                    },
                    {
                        "file": "\/\/v.tvpage.com\/1758166\/132348266\/b68f4\/480p_media.mp4",
                        "quality": "480p",
                        "mime": "video\/mp4",
                        "width": 854,
                        "height": 480
                    },
                    {
                        "file": "\/\/v.tvpage.com\/1758166\/132348266\/b68f4\/360p_media.mp4",
                        "quality": "360p",
                        "mime": "video\/mp4",
                        "width": 640,
                        "height": 360
                    },
                    {
                        "file": "\/\/v.tvpage.com\/1758166\/132348266\/b68f4\/240p_media.mp4",
                        "quality": "240p",
                        "mime": "video\/mp4",
                        "width": 320,
                        "height": 180
                    }
                ]
            },
            "parentId": "6410338",
            "url": "\/gifting\/fitboardwhitebackground-mp4\/6410338-132348266"
        },
        {
            "id": "132348264",
            "title": "Get Creative with a Gift Card",
            "date_created": "1512398973",
            "loginId": "1758166",
            "tags": "",
            "description": "Here's an idea to upgrade the gifting of a gift card.",
            "asset": {
                "user": {
                    "firstName": "",
                    "lastName": "",
                    "emailAddress": ""
                },
                "videoMeta": {
                    "duration": "42",
                    "width": 1920,
                    "height": 1080
                },
                "mediaDuration": "42",
                "prettyDuration": "00:00:42",
                "thumbnailUrl": "\/\/sitecdn.tvpage.com\/live\/users\/1758166\/canvas\/1920\/1077\/482180241-0219201079.jpg",
                "type": "mp4",
                "dashUrl": "\/\/v.tvpage.com\/1758166\/132348264\/2ffdc\/media.mpd",
                "hlsUrl": "\/\/v.tvpage.com\/1758166\/132348264\/2ffdc\/media.m3u8",
                "uploadAsset": false,
                "quality": "",
                "cc": [
                    {
                        "label": "English",
                        "srclang": "en",
                        "src": "\/\/v.tvpage.com\/1758166\/132348264\/cc\/vtt\/en_1516754932.vtt",
                        "default": true
                    }
                ],
                "sources": [
                    {
                        "file": "\/\/v.tvpage.com\/1758166\/132348264\/2ffdc\/1080p_media.mp4",
                        "quality": "1080p",
                        "mime": "video\/mp4",
                        "width": 1920,
                        "height": 1080
                    },
                    {
                        "file": "\/\/v.tvpage.com\/1758166\/132348264\/2ffdc\/720p_media.mp4",
                        "quality": "720p",
                        "mime": "video\/mp4",
                        "width": 1280,
                        "height": 720
                    },
                    {
                        "file": "\/\/v.tvpage.com\/1758166\/132348264\/2ffdc\/480p_media.mp4",
                        "quality": "480p",
                        "mime": "video\/mp4",
                        "width": 854,
                        "height": 480
                    },
                    {
                        "file": "\/\/v.tvpage.com\/1758166\/132348264\/2ffdc\/360p_media.mp4",
                        "quality": "360p",
                        "mime": "video\/mp4",
                        "width": 640,
                        "height": 360
                    },
                    {
                        "file": "\/\/v.tvpage.com\/1758166\/132348264\/2ffdc\/240p_media.mp4",
                        "quality": "240p",
                        "mime": "video\/mp4",
                        "width": 320,
                        "height": 180
                    }
                ]
            },
            "parentId": "6410338",
            "url": "\/gifting\/animalswhite-mp4\/6410338-132348264"
        },
        {
            "id": "132813560",
            "title": "DIY Gift Bag for the Jetsetter",
            "date_created": "1512759203",
            "loginId": "1758166",
            "tags": "",
            "description": "Looking for a great gift for someone always on the go? Want to add a special personal touch? Check out some of our personalizable items!",
            "asset": {
                "user": {
                    "firstName": "",
                    "lastName": "",
                    "emailAddress": ""
                },
                "videoMeta": {
                    "duration": "38",
                    "width": 1920,
                    "height": 1080
                },
                "mediaDuration": "38",
                "prettyDuration": "00:00:38",
                "thumbnailUrl": "\/\/sitecdn.tvpage.com\/live\/users\/1758166\/canvas\/1920\/1077\/584996201-0219201079.jpg",
                "type": "mp4",
                "dashUrl": "\/\/v.tvpage.com\/1758166\/132813560\/36079\/media.mpd",
                "hlsUrl": "\/\/v.tvpage.com\/1758166\/132813560\/36079\/media.m3u8",
                "uploadAsset": false,
                "quality": "",
                "cc": [
                    {
                        "label": "English",
                        "srclang": "en",
                        "src": "\/\/v.tvpage.com\/1758166\/132813560\/cc\/vtt\/en_1516755616.vtt",
                        "default": true
                    }
                ],
                "sources": [
                    {
                        "file": "\/\/v.tvpage.com\/1758166\/132813560\/36079\/1080p_media.mp4",
                        "quality": "1080p",
                        "mime": "video\/mp4",
                        "width": 1920,
                        "height": 1080
                    },
                    {
                        "file": "\/\/v.tvpage.com\/1758166\/132813560\/36079\/720p_media.mp4",
                        "quality": "720p",
                        "mime": "video\/mp4",
                        "width": 1280,
                        "height": 720
                    },
                    {
                        "file": "\/\/v.tvpage.com\/1758166\/132813560\/36079\/480p_media.mp4",
                        "quality": "480p",
                        "mime": "video\/mp4",
                        "width": 854,
                        "height": 480
                    },
                    {
                        "file": "\/\/v.tvpage.com\/1758166\/132813560\/36079\/360p_media.mp4",
                        "quality": "360p",
                        "mime": "video\/mp4",
                        "width": 640,
                        "height": 360
                    },
                    {
                        "file": "\/\/v.tvpage.com\/1758166\/132813560\/36079\/240p_media.mp4",
                        "quality": "240p",
                        "mime": "video\/mp4",
                        "width": 320,
                        "height": 180
                    }
                ]
            },
            "parentId": "6410338",
            "url": "\/gifting\/jetsetter-16x9-mp4\/6410338-132813560"
        },
        {
            "id": "132813559",
            "title": "DIY Gift Bag for the Glam Girl",
            "date_created": "1512759142",
            "loginId": "1758166",
            "tags": "",
            "description": "Looking for a glamorous gift to give? Want to add a special personal touch? Check out some of our personalizable items!",
            "asset": {
                "user": {
                    "firstName": "",
                    "lastName": "",
                    "emailAddress": ""
                },
                "videoMeta": {
                    "duration": "24",
                    "width": 1920,
                    "height": 1080
                },
                "mediaDuration": "24",
                "prettyDuration": "00:00:24",
                "thumbnailUrl": "\/\/sitecdn.tvpage.com\/live\/users\/1758166\/canvas\/1920\/1077\/125306173-0219201079.jpg",
                "type": "mp4",
                "dashUrl": "\/\/v.tvpage.com\/1758166\/132813559\/b8c02\/media.mpd",
                "hlsUrl": "\/\/v.tvpage.com\/1758166\/132813559\/b8c02\/media.m3u8",
                "uploadAsset": false,
                "quality": "",
                "cc": [
                    {
                        "label": "English",
                        "srclang": "en",
                        "src": "\/\/v.tvpage.com\/1758166\/132813559\/cc\/vtt\/en_1516755646.vtt",
                        "default": true
                    }
                ],
                "sources": [
                    {
                        "file": "\/\/v.tvpage.com\/1758166\/132813559\/b8c02\/1080p_media.mp4",
                        "quality": "1080p",
                        "mime": "video\/mp4",
                        "width": 1920,
                        "height": 1080
                    },
                    {
                        "file": "\/\/v.tvpage.com\/1758166\/132813559\/b8c02\/720p_media.mp4",
                        "quality": "720p",
                        "mime": "video\/mp4",
                        "width": 1280,
                        "height": 720
                    },
                    {
                        "file": "\/\/v.tvpage.com\/1758166\/132813559\/b8c02\/480p_media.mp4",
                        "quality": "480p",
                        "mime": "video\/mp4",
                        "width": 854,
                        "height": 480
                    },
                    {
                        "file": "\/\/v.tvpage.com\/1758166\/132813559\/b8c02\/360p_media.mp4",
                        "quality": "360p",
                        "mime": "video\/mp4",
                        "width": 640,
                        "height": 360
                    },
                    {
                        "file": "\/\/v.tvpage.com\/1758166\/132813559\/b8c02\/240p_media.mp4",
                        "quality": "240p",
                        "mime": "video\/mp4",
                        "width": 320,
                        "height": 180
                    }
                ]
            },
            "parentId": "6410338",
            "url": "\/gifting\/glam-girl-16x9-mp4\/6410338-132813559"
        },
        {
            "id": "85297235",
            "title": "New eos Shimmer lip balm \u2013 For delightfully soft Lips",
            "date_created": "1486430932",
            "loginId": "1758166",
            "tags": null,
            "description": "Moisturize, soften and enhance your beautiful smile with a lip balm that delivers lasting moisturization plus a touch of shimmer and shine.",
            "asset": {
                "type": "youtube",
                "author": "eos Products",
                "hdvFlag": 1,
                "description": "Moisturize, soften and enhance your beautiful smile with a lip balm that delivers lasting moisturization plus a touch of shimmer and shine. http:\/\/bit.ly\/shimmersp",
                "tags": "",
                "thumbnailUrl": "https:\/\/i.ytimg.com\/vi\/T96LZ3DCx-o\/hqdefault.jpg",
                "videoId": "T96LZ3DCx-o",
                "mediaDuration": 15,
                "prettyDuration": "00:00:15",
                "uploadAsset": false,
                "quality": ""
            },
            "parentId": "6410338",
            "url": "\/gifting\/new-eos-shimmer-lip-balm-for-delightfully-soft-lips\/6410338-85297235"
        },
        {
            "id": "85297236",
            "title": "eos organic lip balm- for delightfully soft lips",
            "date_created": "1486430951",
            "loginId": "1758166",
            "tags": null,
            "description": "eos organic lip balms are delightfully flavored and packed with antioxidant-rich vitamin E, soothing shea butter, and jojoba oil. These natural lip balms are hypoallergenic, dermatologist tested, and paraben and petrolatum free for soft, smooth, beautiful lips.",
            "asset": {
                "type": "youtube",
                "author": "eos Products",
                "hdvFlag": 1,
                "description": "eos organic lip balms are delightfully flavored and packed with antioxidant-rich vitamin E, soothing shea butter, and jojoba oil. These natural lip balms are hypoallergenic, dermatologist tested, and paraben and petrolatum free for soft, smooth, beautiful lips. https:\/\/evolutionofsmooth.com\/lip-balm.html",
                "tags": "",
                "thumbnailUrl": "https:\/\/i.ytimg.com\/vi\/UlVXJaIFDcc\/hqdefault.jpg",
                "videoId": "UlVXJaIFDcc",
                "mediaDuration": 15,
                "prettyDuration": "00:00:15",
                "uploadAsset": false,
                "quality": ""
            },
            "parentId": "6410338",
            "url": "\/gifting\/eos-organic-lip-balm-for-delightfully-soft-lips\/6410338-85297236"
        },
        {
            "id": "85297237",
            "title": "eos Body Lotions - Delightfully soft skin!",
            "date_created": "1486430958",
            "loginId": "1758166",
            "tags": null,
            "description": "Introducing eos Body Lotions, moisturizing and beautifully scented for delightfully soft skin. Available in Berry Blossom and Delicate Petals scents. Learn more at http:\/\/bit.ly\/berry-blossom-blotion\n\n\nMusic - \"Blue Pool\" by Vanessa Carlton",
            "asset": {
                "type": "youtube",
                "author": "eos Products",
                "hdvFlag": 1,
                "description": "Introducing eos Body Lotions, moisturizing and beautifully scented for delightfully soft skin. Available in Berry Blossom and Delicate Petals scents. Learn more at http:\/\/bit.ly\/berry-blossom-blotion\n\n\nMusic - \"Blue Pool\" by Vanessa Carlton",
                "tags": "",
                "thumbnailUrl": "https:\/\/i.ytimg.com\/vi\/dHyPPvksUTs\/hqdefault.jpg",
                "videoId": "dHyPPvksUTs",
                "mediaDuration": 15,
                "prettyDuration": "00:00:15",
                "uploadAsset": false,
                "quality": ""
            },
            "parentId": "6410338",
            "url": "\/gifting\/eos-body-lotions-delightfully-soft-skin\/6410338-85297237"
        },
        {
            "id": "66858726",
            "title": "How to Pomp a Pompadour | AXE | Instagroom",
            "date_created": "1452628397",
            "loginId": "1758166",
            "tags": "",
            "description": "This is how Ned keeps it real: step by step, pomp by pump. \n\nTHE STEPS:\n1. Blow-dry \n2. Rub pomade on hands\n3. Rake through hair\n4. Pump it up with a comb\n\nSubscribe to the AXE channel for more grooming tips.",
            "asset": {
                "type": "youtube",
                "thumbnailUrl": "https:\/\/i.ytimg.com\/vi\/SFmcWBAraK4\/hqdefault.jpg",
                "uploadDate": 1452628397,
                "videoId": "SFmcWBAraK4",
                "title": "How to Pomp a Pompadour | AXE | Instagroom",
                "description": "This is how Ned keeps it real: step by step, pomp by pump. \n\nTHE TOOLS:\nAXE Signature Clean Cut Look Classic Pomade http:\/\/axe.us\/products\/clean-cut-look-classic-pomade\/?utm_medium=referral&utm_source=instagroom&utm_campaign=ALWAYS_ON_Non_Search_CN000631_CH1211_BH0045_US&utm_term=how-to-pomp-a-pompadour&utm_content=desc\nBlow-dryer\nComb\n\nTHE STEPS:\n1. Blow-dry \n2. Rub pomade on hands\n3. Rake through hair\n4. Pump it up with a comb\n\nSubscribe to the AXE channel for more grooming tips.",
                "author": "AXE",
                "mediaDuration": 15,
                "prettyDuration": "00:00:15",
                "views": "59453",
                "uploadAsset": false,
                "quality": ""
            },
            "parentId": "6410338",
            "url": "\/gifting\/how-to-pomp-a-pompadour-axe-instagroom\/6410338-66858726"
        },
        {
            "id": "66858725",
            "title": "How to Shape an Afro Fade | AXE | Instagroom",
            "date_created": "1452628413",
            "loginId": "1758166",
            "tags": "",
            "description": "This is Afro Fade \u00e0 la Leroy. Crazy but contained. \n\nTHE TOOLS:\nAXE Natural Look Softening Cream\nHair pick\nCurl sponge\n\nTHE STEPS:\n1. Pick hair\n2. Rub cream into palms\n3. Squeeze into hair\n4. Sponge for curls\n\nSubscribe to the AXE channel for more grooming tips.",
            "asset": {
                "type": "youtube",
                "thumbnailUrl": "https:\/\/i.ytimg.com\/vi\/19HZR9rD0ww\/hqdefault.jpg",
                "uploadDate": 1452628413,
                "videoId": "19HZR9rD0ww",
                "title": "How to Shape an Afro Fade | AXE | Instagroom",
                "description": "This is Afro Fade \u00e0 la Leroy. Crazy but contained. \n\nTHE TOOLS:\nAXE Natural Look Softening Cream http:\/\/axe.us\/products\/natural-look-softening-cream\/?utm_medium=referral&utm_source=instagroom&utm_campaign=ALWAYS_ON_Non_Search_CN000631_CH1211_BH0045_US&utm_term=how-to-shape-an-afro-fade&utm_content=desc\nHair pick\nCurl sponge\n\nTHE STEPS:\n1. Pick hair\n2. Rub cream into palms\n3. Squeeze into hair\n4. Sponge for curls\n\nSubscribe to the AXE channel for more grooming tips.",
                "author": "AXE",
                "mediaDuration": 15,
                "prettyDuration": "00:00:15",
                "views": "6123",
                "uploadAsset": false,
                "quality": ""
            },
            "parentId": "6410338",
            "url": "\/gifting\/how-to-shape-an-afro-fade-axe-instagroom\/6410338-66858725"
        },
        {
            "id": "66858724",
            "title": "How to Curl a Low Fade | AXE | Instagroom",
            "date_created": "1452628427",
            "loginId": "1758166",
            "tags": "",
            "description": "Watch Kel jam his low fade in a few smooth moves. Boom. Dancefloor\u2019s calling. \n\nTHE TOOLS:\nAXE Natural Look Softening Cream\nCurl sponge\n\nTHE STEPS:\n1. Rub cream on hands\n2. Rub through hair\n3. Sponge for a nice texture\n\nSubscribe to the AXE channel for more grooming tips.",
            "asset": {
                "type": "youtube",
                "thumbnailUrl": "https:\/\/i.ytimg.com\/vi\/ju6R-lU8-cU\/hqdefault.jpg",
                "uploadDate": 1452628427,
                "videoId": "ju6R-lU8-cU",
                "title": "How to Curl a Low Fade | AXE | Instagroom",
                "description": "Watch Kel jam his low fade in a few smooth moves. Boom. Dancefloor\u2019s calling. \n\nTHE TOOLS:\nAXE Natural Look Softening Cream http:\/\/axe.us\/products\/natural-look-softening-cream\/?utm_medium=referral&utm_source=instagroom&utm_campaign=ALWAYS_ON_Non_Search_CN000631_CH1211_BH0045_US&utm_term=how-to-curl-a-low-fade&utm_content=desc\nCurl sponge\n\nTHE STEPS:\n1. Rub cream on hands\n2. Rub through hair\n3. Sponge for a nice texture\n\nSubscribe to the AXE channel for more grooming tips.",
                "author": "AXE",
                "mediaDuration": 15,
                "prettyDuration": "00:00:15",
                "views": "7638",
                "uploadAsset": false,
                "quality": ""
            },
            "parentId": "6410338",
            "url": "\/gifting\/how-to-curl-a-low-fade-axe-instagroom\/6410338-66858724"
        },
        {
            "id": "66858717",
            "title": "How to Middle Part | AXE |  Instagroom",
            "date_created": "1452628441",
            "loginId": "1758166",
            "tags": "",
            "description": "This is how Joe styles his middle part. He is a little quiet, so he lets his hair do the talking.  \n\nTHE TOOLS:\nAxe Urban Messy Look Flexible Paste \n\nTHE STEPS:\n1. Rub paste into palms\n2. Rake roughly\n3. Part in the middle\n\nSubscribe to the AXE channel for more grooming tips.",
            "asset": {
                "type": "youtube",
                "thumbnailUrl": "https:\/\/i.ytimg.com\/vi\/AqXkOSilfJ4\/hqdefault.jpg",
                "uploadDate": 1452628441,
                "videoId": "AqXkOSilfJ4",
                "title": "How to Middle Part | AXE |  Instagroom",
                "description": "This is how Joe styles his middle part. He is a little quiet, so he lets his hair do the talking.  \n\nTHE TOOLS:\nAxe Urban Messy Look Flexible Paste http:\/\/axe.us\/products\/messy-look-flexible-paste\/?utm_medium=referral&utm_source=instagroom&utm_campaign=ALWAYS_ON_Non_Search_CN000631_CH1211_BH0045_US&utm_term=how-to-middle-part&utm_content=desc\n\nTHE STEPS:\n1. Rub paste into palms\n2. Rake roughly\n3. Part in the middle\n\nSubscribe to the AXE channel for more grooming tips.",
                "author": "AXE",
                "mediaDuration": 15,
                "prettyDuration": "00:00:15",
                "views": "4320",
                "uploadAsset": false,
                "quality": ""
            },
            "parentId": "6410338",
            "url": "\/gifting\/how-to-middle-part-axe-instagroom\/6410338-66858717"
        },
        {
            "id": "66858719",
            "title": "How to Blow-dry Hair | AXE | Instagroom",
            "date_created": "1452628468",
            "loginId": "1758166",
            "tags": "",
            "description": "Most guys don\u2019t blow-dry their hair, but Didyer has his smooth method that shows you how to get the most out of a blowout.\n\nTHE TOOLS:\nAXE Urban Messy Look Flexible Paste\n\nTHE STEPS:\n1. Towel dry\n2. Warm paste on hands\n3. Put hairdryer on medium heat\n4. Brush from front to back give hair volume\n\nSubscribe to the AXE channel for more grooming tips.",
            "asset": {
                "type": "youtube",
                "thumbnailUrl": "https:\/\/i.ytimg.com\/vi\/Y4PQLfZE_cc\/hqdefault.jpg",
                "uploadDate": 1452628468,
                "videoId": "Y4PQLfZE_cc",
                "title": "How to Blow-dry Hair | AXE | Instagroom",
                "description": "Most guys don\u2019t blow-dry their hair, but Didyer has his smooth method that shows you how to get the most out of a blowout.\n\nTHE TOOLS:\nAXE Urban Messy Look Flexible Paste http:\/\/axe.us\/products\/messy-look-flexible-paste\/?utm_medium=referral&utm_source=instagroom&utm_campaign=ALWAYS_ON_Non_Search_CN000631_CH1211_BH0045_US&utm_term=how-to-blow-dry-hair&utm_content=desc\n\nTHE STEPS:\n1. Towel dry\n2. Warm paste on hands\n3. Put hairdryer on medium heat\n4. Brush from front to back give hair volume\n\nSubscribe to the AXE channel for more grooming tips.",
                "author": "AXE",
                "mediaDuration": 15,
                "prettyDuration": "00:00:15",
                "views": "8984",
                "uploadAsset": false,
                "quality": ""
            },
            "parentId": "6410338",
            "url": "\/gifting\/how-to-blow-dry-hair-axe-instagroom\/6410338-66858719"
        },
        {
            "id": "66858714",
            "title": "How to Do a Mohawk | AXE | Instagroom",
            "date_created": "1452628629",
            "loginId": "1758166",
            "tags": "",
            "description": "Becky is a proud mohawker. This is how she keeps it bold. \n\nTHE TOOLS:\nAXE Adrenaline Spiked-Up Look Day Long Glue\n\nTHE STEPS:\n1. Rub glue in hair\n2. Blast it back with a hairdryer \n3. Get more glue and shape\n\nSubscribe to the AXE channel for more grooming tips.",
            "asset": {
                "type": "youtube",
                "thumbnailUrl": "https:\/\/i.ytimg.com\/vi\/XXiUvkRepWs\/hqdefault.jpg",
                "uploadDate": 1452628629,
                "videoId": "XXiUvkRepWs",
                "title": "How to Do a Mohawk | AXE | Instagroom",
                "description": "Becky is a proud mohawker. This is how she keeps it bold. \n\nTHE TOOLS:\nAXE Adrenaline Spiked-Up Look Day Long Glue http:\/\/axe.us\/products\/spiked-up-look-day-long-glue\/?utm_medium=referral&utm_source=instagroom&utm_campaign=ALWAYS_ON_Non_Search_CN000631_CH1211_BH0045_US&utm_term=how-to-do-a-mohawk&utm_content=desc\n\nTHE STEPS:\n1. Rub glue in hair\n2. Blast it back with a hairdryer \n3. Get more glue and shape\n\nSubscribe to the AXE channel for more grooming tips.",
                "author": "AXE",
                "mediaDuration": 15,
                "prettyDuration": "00:00:15",
                "views": "13840",
                "uploadAsset": false,
                "quality": ""
            },
            "parentId": "6410338",
            "url": "\/gifting\/how-to-do-a-mohawk-axe-instagroom\/6410338-66858714"
        },
        {
            "id": "66858713",
            "title": "How to Do Wild Hair | AXE | Instagroom",
            "date_created": "1452628646",
            "loginId": "1758166",
            "tags": "",
            "description": "This is how Jonah channels his inner warrior: with a wild, messy hairdo. \n\nTHE TOOLS:\nAXE Urban Messy Look Matte Gel \n\nTHE STEPS:\n1. Towel dry\n2. Squeeze a blob of gel into hair\n3. Mess it up\n\nSubscribe to the AXE channel for more grooming tips.",
            "asset": {
                "type": "youtube",
                "thumbnailUrl": "https:\/\/i.ytimg.com\/vi\/4yq_tMtcbsA\/hqdefault.jpg",
                "uploadDate": 1452628646,
                "videoId": "4yq_tMtcbsA",
                "title": "How to Do Wild Hair | AXE | Instagroom",
                "description": "This is how Jonah channels his inner warrior: with a wild, messy hairdo. \n\nTHE TOOLS:\nAXE Urban Messy Look Matte Gel http:\/\/axe.us\/products\/messy-look-matte-gel\/?utm_medium=referral&utm_source=instagroom&utm_campaign=ALWAYS_ON_Non_Search_CN000631_CH1211_BH0045_US&utm_term=how-to-do-wild-hair&utm_content=desc\n\nTHE STEPS:\n1. Towel dry\n2. Squeeze a blob of gel into hair\n3. Mess it up\n\nSubscribe to the AXE channel for more grooming tips.",
                "author": "AXE",
                "mediaDuration": 15,
                "prettyDuration": "00:00:15",
                "views": "9261",
                "uploadAsset": false,
                "quality": ""
            },
            "parentId": "6410338",
            "url": "\/gifting\/how-to-do-wild-hair-axe-instagroom\/6410338-66858713"
        },
        {
            "id": "66858712",
            "title": "How to Style a Side Part | AXE | Instagroom",
            "date_created": "1452628659",
            "loginId": "1758166",
            "tags": "",
            "description": "Matteo is a perfectionist. His right side is always right.\n\nTHE TOOLS:\nAXE Signature Clean Cut Look Classic Pomade \n\nTHE STEPS:\n1. Blow-dry \n2. Rub pomade through hair\n3. Part with a comb\n4. Swoop to the right\n\nSubscribe to the AXE channel for more grooming tips.",
            "asset": {
                "type": "youtube",
                "thumbnailUrl": "https:\/\/i.ytimg.com\/vi\/3Yh9y86c-pA\/hqdefault.jpg",
                "uploadDate": 1452628659,
                "videoId": "3Yh9y86c-pA",
                "title": "How to Style a Side Part | AXE | Instagroom",
                "description": "Matteo is a perfectionist. His right side is always right.\n\nTHE TOOLS:\nAXE Signature Clean Cut Look Classic Pomade http:\/\/axe.us\/products\/clean-cut-look-classic-pomade\/?utm_medium=referral&utm_source=instagroom&utm_campaign=ALWAYS_ON_Non_Search_CN000631_CH1211_BH0045_US&utm_term=how-to-style-a-side-part&utm_content=desc\n\nTHE STEPS:\n1. Blow-dry (https:\/\/www.youtube.com\/watch?v=Y4PQLfZE_cc&list=PLDYVec6pytXv622g-agslTcOyR1PIfQLd&index=6)\n2. Rub pomade through hair\n3. Part with a comb\n4. Swoop to the right\n\nSubscribe to the AXE channel for more grooming tips.",
                "author": "AXE",
                "mediaDuration": 15,
                "prettyDuration": "00:00:15",
                "views": "18347",
                "uploadAsset": false,
                "quality": ""
            },
            "parentId": "6410338",
            "url": "\/gifting\/how-to-style-a-side-part-axe-instagroom\/6410338-66858712"
        },
        {
            "id": "66858711",
            "title": "How to Style a Fade Hair | AXE | Instagroom",
            "date_created": "1452628675",
            "loginId": "1758166",
            "tags": "",
            "description": "Ruben likes to sleep longer and groom faster. This is how he perfected his morning fade hair routine.  \n\nTHE TOOLS:\nAXE Urban Messy Look Flexible Paste \n\nTHE STEPS:\n1. Blow-dry\n2. Rub paste on hands\n3. Spread over hair\n4. Rake and squeeze from front to back\n\nSubscribe to the AXE channel for more grooming tips.",
            "asset": {
                "type": "youtube",
                "thumbnailUrl": "https:\/\/i.ytimg.com\/vi\/odDtT-OqcoI\/hqdefault.jpg",
                "uploadDate": 1452628675,
                "videoId": "odDtT-OqcoI",
                "title": "How to Style a Fade Hair | AXE | Instagroom",
                "description": "Ruben likes to sleep longer and groom faster. This is how he perfected his morning fade hair routine.  \n\nTHE TOOLS:\nAXE Urban Messy Look Flexible Paste http:\/\/axe.us\/products\/messy-look-flexible-paste\/?utm_medium=referral&utm_source=instagroom&utm_campaign=ALWAYS_ON_Non_Search_CN000631_CH1211_BH0045_US&utm_term=how-to-style-a-fade-hair&utm_content=desc\n\nTHE STEPS:\n1. Blow-dry\n2. Rub paste on hands\n3. Spread over hair\n4. Rake and squeeze from front to back\n\nSubscribe to the AXE channel for more grooming tips.",
                "author": "AXE",
                "mediaDuration": 15,
                "prettyDuration": "00:00:15",
                "views": "31147",
                "uploadAsset": false,
                "quality": ""
            },
            "parentId": "6410338",
            "url": "\/gifting\/how-to-style-a-fade-hair-axe-instagroom\/6410338-66858711"
        },
        {
            "id": "66858710",
            "title": "How to Do a Man Bun | AXE | Instagroom",
            "date_created": "1452628689",
            "loginId": "1758166",
            "tags": "",
            "description": "This is how Teo ties his hair before playing football. Vamos! \n\nTHE TOOLS:\nAXE Natural Look Softening Cream \nHairband\n\nTHE STEPS:\n1. Mix cream between fingers\n2. Rake into bun\n3. Lock it with a hairband\n\nSubscribe to the AXE channel for more grooming tips.",
            "asset": {
                "type": "youtube",
                "thumbnailUrl": "https:\/\/i.ytimg.com\/vi\/XDlmz9mKvh4\/hqdefault.jpg",
                "uploadDate": 1452628689,
                "videoId": "XDlmz9mKvh4",
                "title": "How to Do a Man Bun | AXE | Instagroom",
                "description": "This is how Teo ties his hair before playing football. Vamos! \n\nTHE TOOLS:\nAXE Natural Look Softening Cream http:\/\/axe.us\/products\/natural-look-softening-cream\/?utm_medium=referral&utm_source=instagroom&utm_campaign=ALWAYS_ON_Non_Search_CN000631_CH1211_BH0045_US&utm_term=how-to-do-a-man-bun&utm_content=desc\nHairband\n\nTHE STEPS:\n1. Mix cream between fingers\n2. Rake into bun\n3. Lock it with a hairband\n\nSubscribe to the AXE channel for more grooming tips.",
                "author": "AXE",
                "mediaDuration": 15,
                "prettyDuration": "00:00:15",
                "views": "10311",
                "uploadAsset": false,
                "quality": ""
            },
            "parentId": "6410338",
            "url": "\/gifting\/how-to-do-a-man-bun-axe-instagroom\/6410338-66858710"
        },
        {
            "id": "85541406",
            "title": "Avalon Organics\u00ae Brand Essence",
            "date_created": "1487976304",
            "loginId": "1758166",
            "tags": null,
            "description": "Curated from nature\u2019s pure resources, Avalon Organics\u00ae skin care, hair care, and bath & body products are deep-rooted in a profound respect for the earth. Discover beauty that\u2019s beyond skin deep.",
            "asset": {
                "type": "youtube",
                "author": "Avalon Organics",
                "hdvFlag": 1,
                "description": "Curated from nature\u2019s pure resources, Avalon Organics\u00ae skin care, hair care, and bath & body products are deep-rooted in a profound respect for the earth. Discover beauty that\u2019s beyond skin deep.  For more information on Avalon Organics\u00ae products visit:\u00a0www.avalonorganics.com",
                "tags": "",
                "thumbnailUrl": "https:\/\/i.ytimg.com\/vi\/D5PjH1yge4U\/hqdefault.jpg",
                "videoId": "D5PjH1yge4U",
                "mediaDuration": 30,
                "prettyDuration": "00:00:30",
                "uploadAsset": false,
                "quality": ""
            },
            "parentId": "6410338",
            "url": "\/gifting\/avalon-organics-brand-essence\/6410338-85541406"
        }
    ]
}