{
    "title": "Abbyson Living - Dark Brown Leather Reclining Sofa Set",
    "description": "Abbyson Living - Dark Brown Leather Reclining Sofa Set",
    "referenceId": "kj-JuExjjGE",
    "date_created": "1486499581",
    "date_modified": "1487879917",
    "tags": null,
    "sourceId": "4",
    "VIDEO_LENGTH": "SHORT",
    "video_type": "Living_Room",
    "status": "approved",
    "visibility": "1",
    "category_id_1": null,
    "category_id_2": null,
    "category_id_3": null,
    "category_id_4": null,
    "category_id_5": null,
    "Concept": null,
    "mod_request": null,
    "cc_request": null,
    "creator": null,
    "video_classification1": null,
    "user_id": null,
    "id": "85299479",
    "loginId": "1758166",
    "entityType": "1",
    "sortOrder": "27",
    "entityIdParent": "6410336",
    "titleTextEncoded": "Abbyson-Living-Dark-Brown-Leather-Reclining-Sofa-Set",
    "category": null,
    "duration": 89,
    "settings": null,
    "asset": {
        "type": "youtube",
        "author": "Abbyson Living Official",
        "hdvFlag": 1,
        "description": "",
        "tags": "",
        "thumbnailUrl": "https:\/\/i.ytimg.com\/vi\/kj-JuExjjGE\/hqdefault.jpg",
        "videoId": "kj-JuExjjGE",
        "mediaDuration": 89,
        "prettyDuration": "00:01:29",
        "uploadAsset": false,
        "quality": ""
    },
    "delete": null,
    "notes": null,
    "uploader": null,
    "modified_date": null,
    "created_date": null
}